Compiled from "PalindromeRecursive.scala"
public final class PalindromeRecursive$ implements java.io.Serializable {
  public static final PalindromeRecursive$ MODULE$;

  public static {};
    Code:
       0: new           #2                  // class PalindromeRecursive$
       3: dup
       4: invokespecial #16                 // Method "<init>":()V
       7: putstatic     #18                 // Field MODULE$:LPalindromeRecursive$;
      10: return

  public boolean isPalindrome(java.lang.String);
    Code:
       0: aload_1
       1: invokevirtual #34                 // Method java/lang/String.length:()I
       4: iconst_0
       5: if_icmpeq     16
       8: aload_1
       9: invokevirtual #34                 // Method java/lang/String.length:()I
      12: iconst_1
      13: if_icmpne     18
      16: iconst_1
      17: ireturn
      18: getstatic     #39                 // Field scala/collection/StringOps$.MODULE$:Lscala/collection/StringOps$;
      21: getstatic     #44                 // Field scala/Predef$.MODULE$:Lscala/Predef$;
      24: aload_1
      25: invokevirtual #48                 // Method scala/Predef$.augmentString:(Ljava/lang/String;)Ljava/lang/String;
      28: iconst_0
      29: invokevirtual #52                 // Method scala/collection/StringOps$.apply$extension:(Ljava/lang/String;I)C
      32: getstatic     #39                 // Field scala/collection/StringOps$.MODULE$:Lscala/collection/StringOps$;
      35: getstatic     #44                 // Field scala/Predef$.MODULE$:Lscala/Predef$;
      38: aload_1
      39: invokevirtual #48                 // Method scala/Predef$.augmentString:(Ljava/lang/String;)Ljava/lang/String;
      42: aload_1
      43: invokevirtual #34                 // Method java/lang/String.length:()I
      46: iconst_1
      47: isub
      48: invokevirtual #52                 // Method scala/collection/StringOps$.apply$extension:(Ljava/lang/String;I)C
      51: if_icmpne     69
      54: aload_1
      55: iconst_1
      56: aload_1
      57: invokevirtual #34                 // Method java/lang/String.length:()I
      60: iconst_1
      61: isub
      62: invokevirtual #56                 // Method java/lang/String.substring:(II)Ljava/lang/String;
      65: astore_1
      66: goto          0
      69: iconst_0
      70: ireturn

  public void main(java.lang.String[]);
    Code:
       0: getstatic     #44                 // Field scala/Predef$.MODULE$:Lscala/Predef$;
       3: aload_0
       4: ldc           #62                 // String hi
       6: invokevirtual #64                 // Method isPalindrome:(Ljava/lang/String;)Z
       9: invokestatic  #70                 // Method scala/runtime/BoxesRunTime.boxToBoolean:(Z)Ljava/lang/Boolean;
      12: invokevirtual #74                 // Method scala/Predef$.println:(Ljava/lang/Object;)V
      15: getstatic     #44                 // Field scala/Predef$.MODULE$:Lscala/Predef$;
      18: aload_0
      19: ldc           #76                 // String ababa
      21: invokevirtual #64                 // Method isPalindrome:(Ljava/lang/String;)Z
      24: invokestatic  #70                 // Method scala/runtime/BoxesRunTime.boxToBoolean:(Z)Ljava/lang/Boolean;
      27: invokevirtual #79                 // Method scala/Predef$.print:(Ljava/lang/Object;)V
      30: return
}
