Compiled from "ListMod.scala"
public final class ListMod {
  public static scala.collection.immutable.List<java.lang.Object> doubleEachElement(scala.collection.immutable.List<java.lang.Object>);
    Code:
       0: getstatic     #14                 // Field ListMod$.MODULE$:LListMod$;
       3: aload_0
       4: invokevirtual #16                 // Method ListMod$.doubleEachElement:(Lscala/collection/immutable/List;)Lscala/collection/immutable/List;
       7: areturn

  public static void main(java.lang.String[]);
    Code:
       0: getstatic     #14                 // Field ListMod$.MODULE$:LListMod$;
       3: aload_0
       4: invokevirtual #20                 // Method ListMod$.main:([Ljava/lang/String;)V
       7: return
}
