Compiled from "ArrayMod.scala"
public final class ArrayMod {
  public static int[] doubleEachElement(int[]);
    Code:
       0: getstatic     #13                 // Field ArrayMod$.MODULE$:LArrayMod$;
       3: aload_0
       4: invokevirtual #15                 // Method ArrayMod$.doubleEachElement:([I)[I
       7: areturn

  public static void main(java.lang.String[]);
    Code:
       0: getstatic     #13                 // Field ArrayMod$.MODULE$:LArrayMod$;
       3: aload_0
       4: invokevirtual #19                 // Method ArrayMod$.main:([Ljava/lang/String;)V
       7: return
}
